nbpaths/__init__.py
nbpaths/add_parents.py
nbpaths-0.17.dist-info/METADATA
nbpaths-0.17.dist-info/WHEEL
nbpaths-0.17.dist-info/top_level.txt
nbpaths-0.17.dist-info/RECORD
